repsci/__init__.py
repsci-1.1.8.dist-info/LICENSE
repsci-1.1.8.dist-info/METADATA
repsci-1.1.8.dist-info/WHEEL
repsci-1.1.8.dist-info/top_level.txt
repsci-1.1.8.dist-info/RECORD
