Metadata-Version: 2.1
Name: repsci
Version: 1.1.8
Summary: A tool for reproducible scientific computing
Home-page: https://github.com/elplatt/repsci
Author: Edward L. Platt
Author-email: ed@elplatt.com
License: UNKNOWN
Platform: UNKNOWN
Classifier: Programming Language :: Python :: 3
Classifier: License :: OSI Approved :: BSD License
Classifier: Operating System :: OS Independent
Requires-Python: >=3.6
